nanolayer/__init__.py
nanolayer/__main__.py
nanolayer/py.typed
nanolayer/cli/__init__.py
nanolayer/cli/install.py
nanolayer/installers/__init__.py
nanolayer/installers/apk/__init__.py
nanolayer/installers/apk/apk_installer.py
nanolayer/installers/apt/__init__.py
nanolayer/installers/apt/apt_installer.py
nanolayer/installers/apt_get/__init__.py
nanolayer/installers/apt_get/apt_get_installer.py
nanolayer/installers/aptitude/__init__.py
nanolayer/installers/aptitude/aptitude_installer.py
nanolayer/installers/devcontainer_feature/__init__.py
nanolayer/installers/devcontainer_feature/oci_feature.py
nanolayer/installers/devcontainer_feature/oci_feature_installer.py
nanolayer/installers/devcontainer_feature/models/__init__.py
nanolayer/installers/devcontainer_feature/models/devcontainer_feature.py
nanolayer/installers/gh_release/__init__.py
nanolayer/installers/gh_release/gh_release_installer.py
nanolayer/installers/gh_release/resolvers/__init__.py
nanolayer/installers/gh_release/resolvers/asset_resolver.py
nanolayer/installers/gh_release/resolvers/binary_resolver.py
nanolayer/installers/gh_release/resolvers/release_resolver.py
nanolayer/installers/gh_release/utils/__init__.py
nanolayer/installers/gh_release/utils/abstract_archive.py
nanolayer/installers/gh_release/utils/archive.py
nanolayer/installers/gh_release/utils/compressed_file.py
nanolayer/installers/gh_release/utils/tar_archive.py
nanolayer/installers/gh_release/utils/zip_archive.py
nanolayer/utils/__init__.py
nanolayer/utils/analytics.py
nanolayer/utils/invoker.py
nanolayer/utils/linux_information_desk.py
nanolayer/utils/oci_registry.py
nanolayer/utils/settings.py
nanolayer/utils/version.py
nanolayer-0.5.6.dist-info/METADATA
nanolayer-0.5.6.dist-info/WHEEL
nanolayer-0.5.6.dist-info/entry_points.txt
nanolayer-0.5.6.dist-info/top_level.txt
nanolayer-0.5.6.dist-info/RECORD
