Metadata-Version: 2.1
Name: nanolayer
Version: 0.5.6
Author: Daniel Braun
Requires-Dist: pydantic ==1.10.7
Requires-Dist: typer ==0.7.0
Requires-Dist: invoke ==2.0.0
Requires-Dist: natsort ==8.3.1
Requires-Dist: sentry-sdk ==1.24.0
Provides-Extra: dev
Requires-Dist: pytest ; extra == 'dev'
Requires-Dist: pytest-shell-utilities ; extra == 'dev'
Requires-Dist: black ; extra == 'dev'
Requires-Dist: mypy ; extra == 'dev'
Requires-Dist: gitpython ; extra == 'dev'
Requires-Dist: build ; extra == 'dev'
Requires-Dist: setuptools ; extra == 'dev'
Requires-Dist: wheel ; extra == 'dev'
Requires-Dist: setuptools-scm ; extra == 'dev'
Requires-Dist: packaging ; extra == 'dev'
Requires-Dist: dcontainer >=1.0.6 ; extra == 'dev'
